<annotation>
	<folder>train</folder>
	<filename>banana_67_jpg.rf.4c85b5b1ccab155fa4231d656e45c9c8.jpg</filename>
	<path>C:\Users\etudiant\Downloads\Datasets\Datasets\train\banana_67_jpg.rf.4c85b5b1ccab155fa4231d656e45c9c8.jpg</path>
	<source>
		<database>Unknown</database>
	</source>
	<size>
		<width>640</width>
		<height>640</height>
		<depth>3</depth>
	</size>
	<segmented>0</segmented>
	<object>
		<name>banana</name>
		<pose>Unspecified</pose>
		<truncated>0</truncated>
		<difficult>0</difficult>
		<bndbox>
			<xmin>72</xmin>
			<ymin>103</ymin>
			<xmax>587</xmax>
			<ymax>598</ymax>
		</bndbox>
	</object>
</annotation>
